Workbook

Sheet Bottom-Up Model
B2: Black Text | C2: = Fixed Data Inputs
B3: Blue Text | C3: = Formulas/Calculation
B4: Yellow color coded | C4: = Assumptions
B6: Year 2025 | C6: Urban | D6: Rural | E6: Total
B7: POPULATION
B8: Indonesia Population | C8: 0.6 | D8: 0.4 | E8: 284438800 | G8: Source: | H8: BPS Indonesia Population
B9: Urban/Rural Total | C9: =C8*$E$8 -> 170663280 | D9: =D8*$E$8 -> 113775520 | G9: Source: | H9: BPS Indonesia Urban Population
B12: SMARTPHONE & INTERNET PENETRATION
B13: Smartphone Penetration | C13: 0.7415 | D13: 0.6078 | G13: Source: | H13: BPS Indonesia Smartphone Penetration 2024
C14: =C13*$C$9 -> 1.2654682e+08 | D14: =D13*$D$9 -> 69152761
B15: Internet Penetration | C15: 0.8353 | D15: 0.7696 | G15: Source: | H15: APJII Survey 2025
C16: =C15*$C$14 -> 1.0570456e+08 | D16: =D15*$D$14 -> 53219965
B18: INCOME DISTRIBUTION
B19: Low-Income | C19: 0.4 | D19: 0.5 | G19: Source: | H19: BPS Statistical Yearbook 2025
B20: Middle-Income | C20: 0.4 | D20: 0.4
B21: High-Income | C21: 0.2 | D21: 0.1
B23: Low-Income | C23: =C19*$C$16 -> 42281824 | D23: =D19*$D$16 -> 26609982
B24: Middle-Income | C24: =C20*$C$16 -> 42281824 | D24: =D20*$D$16 -> 21287986
B25: High-Income | C25: =C21*$C$16 -> 21140912 | D25: =D21*$D$16 -> 5321996.5
B28: MOBILE WALLET ADOPTION RATES
B29: Low-Income | C29: 0.2 | D29: 0.05
B30: Middle-Income | C30: 0.4 | D30: 0.3
B31: High-Income | C31: 0.6 | D31: 0.5 | G31: Source: | H31: GoPay Regional Adoption Rates
B33: Low-Income | C33: =C29*C23 -> 8456364.8 | D33: =D29*D23 -> 1330499.1
B34: Middle-Income | C34: =C30*C24 -> 16912730 | D34: =D30*D24 -> 6386395.8
B35: High-Income | C35: =C31*C25 -> 12684547 | D35: =D31*D25 -> 2660998.2
B38: ANNUAL REVENUE PER USER (ARPU) per month (in USD)
B39: Low-Income | C39: ='ARPU Calculation'!C32 -> 0.35 | D39: ='ARPU Calculation'!D32 -> 0.12
B40: Middle-Income | C40: ='ARPU Calculation'!C33 -> 0.75 | D40: ='ARPU Calculation'!D33 -> 0.25
B41: High-Income | C41: ='ARPU Calculation'!C34 -> 1.85 | D41: ='ARPU Calculation'!D34 -> 0.55
B43: Low-Income | C43: =C39*C33*12 -> 35516732 | D43: =D39*D33*12 -> 1915918.7
B44: Middle-Income | C44: =C40*C34*12 -> 1.5221457e+08 | D44: =D40*D34*12 -> 19159187
B45: High-Income | C45: =C41*C35*12 -> 2.8159695e+08 | D45: =D41*D35*12 -> 17562588
B47: Total Addressable Market (TAM)
C48: =SUM(C43:C45) -> 4.6932825e+08 | D48: =SUM(D43:D45) -> 38637695 | E48: =SUM(C48:D48) -> 5.0796594e+08
C49: =C48/E48 -> 0.92393645 | D49: =D48/E48 -> 0.076063553
C51: =C43/$E$48 -> 0.069919515 | D51: =D43/$E$48 -> 0.0037717464
C52: =C44/$E$48 -> 0.29965506 | D52: =D44/$E$48 -> 0.037717464
C53: =C45/$E$48 -> 0.55436187 | D53: =D45/$E$48 -> 0.034574342

Sheet ARPU Calculation
B2: Black Text | C2: = Fixed Data Inputs
B3: Blue Text | C3: = Formulas/Calculation
B4: Yellow color coded | C4: = Assumptions
B6: ANNUAL REVENUE PER USER (ARPU)
B8: Indonesians spend an average of US$35 (approximately 543,250 IDR) on e-commerce purchases each month.
B9: Source: Indonesia E-Commerce Trends, 2024, Jakpat
B11: And, Digital wallets comprise 35% share by volume of the primary payment methods for e-commerce in Indonesia.
B12: PCMI
B14: Avg E-commerce spend/month | C14: 35
B15: Digital Wallet Share | C15: 0.35
B16: Wallet GTV for E-commerce | C16: =C14*C15 -> 12.25 | D16: (GTV - Gross Transaction Value)
B17: Avg Take rate | C17: 0.015 | D17: (the actual % of the transaction wallet provider keeps)
B18: Wallet Revenue (1) | C18: =C16*C17 -> 0.18375
B20: Indonesian users frequently use QRIS for small-ticket, daily, non-e-commerce transactions (foods, transport, bills).
B21: Avg Non E-commerce spend/month | C21: 20
B22: Merchant Discount Rate | C22: 0.007 | D22: (Standard Bank Indonesia rate for regular merchants via QRIS)
B23: Wallet Revenue (2) | C23: =C21*C22 -> 0.14
B25: Other Value added services, like revenue from lending/credit commissions, BNPL etc.
B26: Wallet Revenue (3) | C26: 0.2
B28: Total Monthly ARPU | C28: =SUM(C26,C23,C18) -> 0.52375
B30: ARPU Assumptions
C31: Urban | D31: Rural
B32: Low-Income | C32: 0.35 | D32: 0.12
B33: Middle-Income | C33: 0.75 | D33: 0.25
B34: High-Income | C34: 1.85 | D34: 0.55
B35: - Urban high/mid users are more likely to use BNPL features, hence ARPU is high as VAS service provide better margins for wallet providers.

Sheet Break-Even Calculation
B2: Black Text | C2: = Fixed Data Inputs
B3: Blue Text | C3: = Formulas/Calculation
B4: Yellow color coded | C4: = Assumptions
B6: Break-Even Calculation
B7: On average, the cost to develop a digital wallet app can range from $60,000 to $250,000 or more.
B8: Source: | C8: Digital wallet app development
B10: 34% of users made QRIS transactions two to three times a week, with the majority of transactions involving 100,000 rupiah or less.
B11: Source: | C11: Indonesia's digital payments market
C13: IDR | D13: USD
B14: Fixed Costs | C14: 1700000000 | D14: 1000000
B16: Avg Transaction Value (per month) | C16: 100000
B17: Merchant Discount Rate (MDR) | C17: 0.007
B19: Revenue Split
B20: `- Issuing wallet (50%) | C20: =C17*E20 -> 0.0035 | E20: 0.5
B21: `- Other admin fees (50%) | C21: =C17*E21 -> 0.0035 | E21: 0.5
B23: Variable Costs (per txn) | C23: =C16*C21 -> 350
B25: Break-Even Transactions (per month) | C25: =C14/C23 -> 4857142.9
C26: ~ 5 Million
